{"ocr_results":[{"text":"第六章中央學习班到省革委學習班","box":[[403,86],[710,86],[710,103],[403,103]]},{"text":"了八一五和五十四軍的眼中。","box":[[111,127],[406,127],[406,144],[111,144]]},{"text":"反到底派在推選重市革委會名單時，考到作爲一個地","box":[[154,161],[711,161],[711,181],[154,181]]},{"text":"區，一大批群的代表，一致把邱開全推選爲市革委委員。","box":[[107,195],[677,195],[677,215],[107,215]]},{"text":"名單報上去後不久，白斌找我去，：“邱開全是一個雙","box":[[157,231],[711,231],[711,248],[157,248]]},{"text":"手沾满鮮血的武门韩將，八一五派决反對邱開全進入市革委，","box":[[106,264],[711,265],[711,285],[106,284]]},{"text":"市革等和我們軍部掌握了不少邱開全的材料，希望反到底派自","box":[[107,298],[710,299],[710,319],[107,318]]},{"text":"已研究，把邱開全换成其他人爲好，如果你們硬要把他報上來，","box":[[109,335],[711,335],[711,352],[109,352]]},{"text":"我們也一定要把他的名字掉，我們也要求八一五派不要報阳","box":[[107,368],[712,369],[712,389],[107,388]]},{"text":"增泰，阳增泰也是武门韩将嘛！八一五派就在内部統一了","box":[[107,401],[712,403],[712,424],[107,422]]},{"text":"識，不報陽增泰，另報了其他人。你們也研究研究吧！”","box":[[105,435],[652,434],[652,457],[105,458]]},{"text":"我們反到底派六大司令部在京勤務員，一起研究了邱開","box":[[155,473],[713,473],[713,493],[155,493]]},{"text":"全問题，真研究了半天，按当時的思維惯，就是“凡是","box":[[108,507],[714,507],[714,527],[108,527]]},{"text":"人反對的我們就要護”，你八一五反對的，我們就偏要推選！","box":[[107,540],[707,541],[707,561],[107,560]]},{"text":"大家不後果，一致决定：上報邱開全爲市革委委真，哪怕市","box":[[109,578],[712,578],[712,595],[109,595]]},{"text":"革等和五十四軍硬把邱開全的名字掉，最多是反到底派進入","box":[[107,610],[715,611],[715,631],[107,630]]},{"text":"省、市革委會的名额再少一名，邱開全也非報不可！","box":[[107,644],[610,645],[610,666],[107,664]]},{"text":"為了報邱開全，我還跟白斌半開玩笑地：“八一五","box":[[155,681],[715,681],[715,701],[155,701]]},{"text":"的周家瑜曾經坐在坦克裹指武门，他那坦克也可能開了炮","box":[[107,714],[716,715],[716,735],[107,734]]},{"text":"的，打出去的炮彈也可能打死了人的，你們是不是也要把周家","box":[[106,748],[715,749],[715,770],[106,768]]},{"text":"瑜的名字劃掉？”","box":[[105,783],[271,779],[272,804],[105,807]]},{"text":"名單報上去了，邱開全的名字還是被劃掉了。","box":[[155,818],[592,819],[592,839],[155,838]]},{"text":"反到底派在省、市革委會中的名额就這樣少了兩個。","box":[[155,852],[659,854],[658,875],[155,873]]},{"text":"我們上報的省、市革委會反到底派代表名單，都是由機","box":[[155,888],[716,889],[716,909],[155,908]]},{"text":"司令部段炳森腾清後，由我交上去的。别看段炳森是個四肢發","box":[[107,922],[716,923],[716,943],[107,942]]},{"text":"蓬的重運動員，他却寫得一手好鋼筆字。所以後來當老友們","box":[[108,959],[715,959],[715,977],[108,977]]},{"text":"[1]陽增泰，時為國營重慶朝陽電機廠技術員，文革造反中任八一兵團一號勤務","box":[[105,1025],[717,1025],[717,1045],[105,1045]]},{"text":"員，1967年1月在五十四軍支持下参加對市委、市人委的奪權，2月革聊會","box":[[144,1051],[716,1051],[716,1068],[144,1068]]},{"text":"成立任副主任。1967年7月兩派大规模武门中任八一五派文攻武衛指部","box":[[144,1077],[718,1077],[718,1094],[144,1094]]},{"text":"總指。後調離重慶。以後情况不详。","box":[[143,1102],[428,1102],[428,1119],[143,1119]]},{"text":"·165·","box":[[661,1159],[714,1159],[714,1178],[661,1178]]}],"dimensions":{"height":1228,"width":808}}