{"ocr_results":[{"text":"第十一章脱陰影","box":[[545,84],[707,84],[707,104],[545,104]]},{"text":"第十一章脱陰影","box":[[271,229],[541,229],[541,257],[271,257]]},{"text":"調資晋级一再被卡","box":[[302,333],[510,333],[510,357],[302,357]]},{"text":"粉碎“四人”起，到一九八二年止，六年中就有四","box":[[151,401],[708,402],[708,423],[150,422]]},{"text":"次調資晋級的機會，都没有我的份。一九七七年調資晋級面","box":[[103,435],[709,436],[709,457],[103,456]]},{"text":"是百分之四十，一九七八年是百分之二，一九七九年是百分之","box":[[104,472],[709,472],[709,492],[104,492]]},{"text":"四十，一九八二年是百分之一，四次都因為政治問题即文化大革","box":[[104,505],[709,506],[709,527],[104,526]]},{"text":"命問題，不給我調資晋級。","box":[[104,539],[360,540],[360,562],[104,560]]},{"text":"第一次是在一九七七年十二月進行的。我回廠接受查尚","box":[[149,573],[710,575],[710,598],[148,596]]},{"text":"未結束，正处于第二次大會查完後的一段時間（我是第四次","box":[[103,608],[709,610],[709,631],[103,629]]},{"text":"大會查後才結束查的）。","box":[[103,643],[372,645],[372,666],[103,663]]},{"text":"我李木森是個通情達理的人，按常理，完全可以直接對我","box":[[152,679],[710,679],[710,699],[152,699]]},{"text":"罐，明你是在睿查期間，這次只有百分之四十的名额可以晋","box":[[104,714],[711,714],[711,734],[104,734]]},{"text":"級，你就暂不考了....我深信自己是能够接受的。何况本單","box":[[102,747],[712,748],[712,770],[102,768]]},{"text":"位的同事都是相处十餘年的老同事、老熟人、老同行了，我會","box":[[103,782],[710,784],[710,804],[103,802]]},{"text":"不要面去跟他們爭？","box":[[104,818],[337,818],[337,838],[104,838]]},{"text":"可是，當時我單位的調資晋級工作在某些人的干预下，制","box":[[150,849],[713,852],[713,876],[149,872]]},{"text":"定了調資晋级的進行圍和指標方案，根據名额分，我要和","box":[[102,886],[712,888],[712,909],[102,907]]},{"text":"一位一九五五年進廠的老同事爭一個名额。這不是太明了","box":[[103,921],[711,922],[711,943],[103,942]]},{"text":"？有關人士就是要我去爭，好像恨不得我去争個你死我活的","box":[[103,955],[712,957],[712,978],[103,976]]},{"text":"局面来...","box":[[103,991],[213,991],[213,1011],[103,1011]]},{"text":"我一看就知道不對，經歷過文革的人，對什是“挑起群","box":[[150,1025],[712,1027],[712,1048],[149,1046]]},{"text":"衆們群”是很熟悉，很警惕的。我經過分析，决定放弃競爭，","box":[[103,1059],[713,1061],[713,1083],[103,1081]]},{"text":"镶那位老同事晋級。","box":[[103,1094],[293,1096],[293,1117],[103,1115]]},{"text":"·307.","box":[[653,1159],[711,1156],[712,1177],[654,1180]]}],"dimensions":{"height":1228,"width":808}}