{"ocr_results":[{"text":"138","box":[[127,69],[156,69],[156,88],[127,88]]},{"text":"仰天長啸","box":[[702,69],[774,69],[774,87],[702,87]]},{"text":"要努力向前。冥想中倦意，迷迷糊糊中白天學會的一首紅軍歌曲","box":[[131,129],[772,129],[772,146],[131,146]]},{"text":"在耳畔：士們高著鮮紅的旗勇向前進，配合那全國紅軍要","box":[[130,161],[773,162],[773,182],[130,181]]},{"text":"實行總的反攻。創造新的革命根據地，大家要努力.….努力·…..…，渐","box":[[130,197],[775,197],[775,217],[130,217]]},{"text":"渐便沉入夢鄉之中。","box":[[130,232],[320,232],[320,252],[130,252]]},{"text":"正酣睡時突然被一陣尖锐的哨聲醒，隧長在喊「紧急集合！忙","box":[[174,267],[774,268],[774,288],[174,287]]},{"text":"翻身下床穿衣叠被打绑腿，一看才凌晨三點·隧長作出發前的動員","box":[[131,303],[772,304],[772,322],[131,321]]},{"text":"，「這裹距瑞金优百八十里路程，今天提前出發，爭取擦黑时到蓬","box":[[131,338],[773,340],[773,358],[131,357]]},{"text":"瑞金，在瑞金將休整三天。於是立即開拔。夜空無月，稀星可数，漆","box":[[130,373],[775,374],[775,394],[130,393]]},{"text":"黑一片伸手見五指。田硬的小路很窄、很走，於是都将電筒打亮","box":[[132,411],[773,411],[773,428],[132,428]]},{"text":"照路。走著走著回頭一看，一优复手電筒的亮光，像夜明珠-樣連成","box":[[132,446],[774,446],[774,463],[132,463]]},{"text":"了串。燈光倒映在田硬兩旁的水田裹，上下辉映，波光遵漪，真是美","box":[[131,479],[774,480],[774,500],[131,499]]},{"text":"妙壮觀極了，大家不禁都得「哦，哦」地叫起來。","box":[[130,514],[626,515],[626,535],[130,534]]},{"text":"天大亮時已了三十里路，在一個接待站吃了早饭後又上路。走","box":[[177,551],[774,551],[774,568],[177,568]]},{"text":"不多久又是-座大山，翻過這座山時已經是下午四點，破天荒一莲走","box":[[133,587],[773,587],[773,604],[133,604]]},{"text":"了一百缀十里路，實在是再也走不動了，於是在山下一個时接待","box":[[134,622],[773,622],[773,639],[134,639]]},{"text":"站宿營·接待站設在一座破的古裹，接待人員，此處離瑞金","box":[[132,655],[773,656],[773,676],[132,675]]},{"text":"尚有五十里路。有位男同學一文興蓄起來，要連夜到瑞金·隧","box":[[133,691],[774,692],[774,710],[133,709]]},{"text":"長不同意，但這位同學哪裹得進，稍事休整，補充了水和乾便","box":[[131,725],[774,726],[774,746],[131,745]]},{"text":"急急出發。有雨位女同學币帼不骥眉，也加入了這個「先遭隧」。我","box":[[134,763],[774,763],[774,780],[134,780]]},{"text":"心往之而力不足，只好和大隧明天再走。","box":[[131,795],[538,796],[538,816],[131,815]]},{"text":"夜已深了，我躺在古的草堆上，久久不能入睡。山下寒氣逼","box":[[176,832],[773,833],[773,851],[176,850]]},{"text":"人，垫的的被子都嫌薄了，難以寒，只得把身子蜷成一團以求保","box":[[131,866],[774,867],[774,887],[131,886]]},{"text":"暖·寂静的夜晚裹，耳總能到一些不可捉摸的聲響大山裹傅","box":[[129,901],[773,902],[773,922],[129,921]]},{"text":"來，我忽然想到了初中語文課本中《老山界》那篇課文中描述過的那種","box":[[129,936],[774,937],[774,957],[129,956]]},{"text":"聲響：「極遠的又是極近的，極洪大的又是極細切的，像春在咀嚼桑","box":[[131,972],[772,973],[772,991],[131,990]]},{"text":"葉，像野馬在平原上奔，像山泉在咽，像波在澎湃。』描寫得真","box":[[130,1008],[772,1010],[772,1028],[130,1027]]},{"text":"是太逼真、太傅神了。《老山界》這篇文章，是寫紅軍長征翻越越城嶺","box":[[130,1043],[773,1044],[773,1064],[130,1063]]},{"text":"時的一段經歷，作者原中宣部部長陵定一，是文革初就被打成阎王殿","box":[[128,1077],[773,1080],[773,1100],[128,1097]]},{"text":"的王，反黛反社會主羲反毛澤束思想的「三反分子」。睦定一究竟是","box":[[128,1113],[773,1114],[773,1134],[128,1133]]},{"text":"不是阎王！，是不是|三反分子」，我也不清楚，但他的《老山界》罐寳","box":[[129,1151],[771,1151],[771,1168],[129,1168]]},{"text":"寫得不錯，而且是長征時寫的，不能因人言·想著想著，反正凍得","box":[[127,1183],[772,1186],[772,1206],[127,1203]]},{"text":"大众图书馆http://dztsg.infc","box":[[319,1298],[560,1298],[560,1318],[319,1318]]}],"dimensions":{"height":1346,"width":880}}