{"ocr_results":[{"text":"186","box":[[129,70],[158,70],[158,89],[129,89]]},{"text":"仰天長啸","box":[[698,70],[771,70],[771,87],[698,87]]},{"text":"我一就笑了，這份傅單我也見過，我這個造反派的黑筆悍子","box":[[173,127],[771,129],[771,149],[173,147]]},{"text":"出身大地主大資本家的家庭，父親是國民黛的高级軍官。母親更邪","box":[[131,162],[772,164],[772,184],[131,182]]},{"text":"乎，高鼻子黄頭髮，是國外派遭的高级間課。還我家有一部可事","box":[[131,198],[770,200],[770,218],[131,216]]},{"text":"間課活動的袖珍相機，只有粒麻将大，可以褲福裹往外偷拍照","box":[[130,232],[772,235],[772,254],[130,251]]},{"text":"片…..云云·言自然是造得過於拙劣，不值一，但我家的一些親","box":[[130,267],[771,269],[771,289],[130,287]]},{"text":"戚朋友甚至粼居都念忿不平地替我四處關，連我的一個在漢阳一家","box":[[130,302],[771,305],[771,326],[130,322]]},{"text":"商店工作的鐵杆老保的姑爹都氣不過，那些印傅單的人，是狗咬","box":[[130,337],[771,340],[771,360],[130,358]]},{"text":"巴瞎扯蛋。不過也有一些不太熟識的「戟友」，見到我时十分真地","box":[[130,375],[770,377],[770,395],[130,393]]},{"text":"問我，你母親真是外國人？是哪一國的？還問我能不能把那架可以","box":[[129,409],[770,411],[770,431],[129,429]]},{"text":"褲檔裹往外拍照的袖珍相機拿出來，給他們見識見識，弄得人簡直","box":[[128,444],[770,446],[770,466],[128,464]]},{"text":"哭笑不得。施教授我後直是頭，感慨「曾参殺人」，「三人成","box":[[128,480],[771,482],[771,502],[128,500]]},{"text":"虎」，著實人言可畏。我們又到中央派到武漢來的位大員，怎就","box":[[128,516],[770,518],[770,536],[128,534]]},{"text":"音訊全無了呢？莫非都已遭了「百匪」的暗算？局勢究竟將如何發展，","box":[[126,550],[767,552],[767,572],[126,570]]},{"text":"心裹也實在没有底。","box":[[127,586],[316,586],[316,606],[127,606]]},{"text":"然而到了23日這天，一清早氣氛就與往常不一樣。首先就是窗對","box":[[168,620],[769,623],[769,643],[168,640]]},{"text":"面遠遠高撕在電線悍上的百萬雄師的高音喇叭，到了六點鐘竟不照例","box":[[126,655],[770,658],[770,678],[126,675]]},{"text":"播放「鐘山風雨起黄，百萬雄師過大江的語錄歌了。不但不放，連","box":[[126,691],[770,693],[770,713],[126,711]]},{"text":"一點聲音都没有，令人十分。更令人吃的是百萬雄師據點所在","box":[[126,726],[769,728],[769,748],[126,746]]},{"text":"的那棟樓樓頂上，那面耀武揚威不可一世的旗，竟然也不知何時降","box":[[127,761],[769,763],[769,783],[127,781]]},{"text":"下來了。施教授這倒是有點像抗戳勝利那年，日本人投降的味道。","box":[[128,797],[766,799],[766,819],[128,817]]},{"text":"正叫人費解之時，遠處約約傅來一陣廣播聲，好像是謝副總","box":[[127,832],[769,834],[769,854],[127,852]]},{"text":"理、王力同志什的。忙打開收音機，中央人民廣播電正在播送一","box":[[127,867],[769,870],[769,890],[127,887]]},{"text":"篇消息，说我們偉大领袖毛主席和中央派來處理武汉問题的代表謝","box":[[127,902],[768,905],[768,925],[127,922]]},{"text":"副總理、王力同志等，已於七月二十二日下午由武漢乘專機光榮地回","box":[[128,937],[768,940],[768,960],[128,957]]},{"text":"到北京。中央领導同志周恩來總理、陳伯達、康生、江青等同志，以","box":[[128,973],[768,975],[768,996],[128,993]]},{"text":"及三軍指員和數萬革命群到機場熱烈歡迎，等等。原來如此，難","box":[[129,1008],[769,1012],[769,1032],[129,1028]]},{"text":"怪百萬雄師突然偃旗息鼓，是風向大變了。","box":[[128,1045],[530,1047],[530,1065],[128,1063]]},{"text":"不久就見窗外罐鼓大作，造反派群累都上街载歌戴舞地狂歡起","box":[[171,1081],[766,1083],[766,1100],[171,1098]]},{"text":"來，有不知哪襄突然冒出來的陵海空三軍指員，也攀著和無產","box":[[126,1114],[766,1117],[766,1137],[126,1134]]},{"text":"級革命造反派團結在一起勝利在一起门在一起的旗，匯進了游","box":[[126,1150],[768,1152],[768,1172],[126,1170]]},{"text":"行的洪流·這之後便是北京行熱烈歡迎谢富治、王力「武漢勝利","box":[[123,1185],[767,1187],[767,1207],[123,1205]]},{"text":"大众图书馆http://dztsg.infc","box":[[319,1298],[560,1298],[560,1318],[319,1318]]}],"dimensions":{"height":1346,"width":880}}