{"ocr_results":[{"text":"第十六章蓬摩克利斯之劍","box":[[94,70],[318,70],[318,87],[94,87]]},{"text":"399","box":[[714,71],[741,71],[741,89],[714,89]]},{"text":"我於死其實是有所備的。「反漫]如真正坐實了，是砍頭的","box":[[140,129],[738,129],[738,146],[140,146]]},{"text":"的大罪，我如何心中無？「漫」的間題我一日解耦不清楚，我頭頂","box":[[94,162],[741,163],[741,183],[94,182]]},{"text":"上著的那柄蓬摩克利斯劍，就随時都可能落下來。而我又如何能将","box":[[96,199],[739,199],[739,216],[96,216]]},{"text":"那個胡寫鼠畫的該死的漫解耦清楚呢？莫非是天亡我]乎？","box":[[95,235],[701,235],[701,252],[95,252]]},{"text":"當然這些都是我自已在胡思凱想，我业没有被拉出去「大劈」。但","box":[[141,270],[740,270],[740,287],[141,287]]},{"text":"是隔一段時間，少则十缀天多则個把月，總會有人來提提蕃，我交","box":[[96,305],[740,305],[740,322],[96,322]]},{"text":"代「漫」的問題，而我總是以客觀上玷污损害了偉大领袖的形象但無","box":[[93,339],[741,337],[741,358],[93,359]]},{"text":"主觀動機來「搪塞」·這種「塘塞]自然不能令提密的人滿意，他們需要","box":[[94,374],[741,375],[741,395],[94,394]]},{"text":"的是我|坦百交代]自己寫何舆如何|总攻的罪行。他們只有坦百交","box":[[96,412],[740,412],[740,429],[96,429]]},{"text":"代了罪行才能識罪行，才能接受他們的「挽救」，才能「重新做人」，","box":[[94,446],[749,445],[749,465],[94,466]]},{"text":"總之他們對我是非常的仁至羲。","box":[[96,482],[418,482],[418,499],[96,499]]},{"text":"但是我知道鲁迅先生早就過，那仁羲道德的字縫中寫的是兩","box":[[141,517],[740,517],[740,534],[141,534]]},{"text":"個字「吃人」，是「子的凶心、兔子的怯弱、狐狸的狡猜」，「他們大家","box":[[95,552],[740,551],[740,569],[95,570]]},{"text":"連絡，怖滿了羅網，逼我自。」我心明肚亮，不他們的羅網，","box":[[94,586],[741,585],[741,605],[94,606]]},{"text":"不自，绝不承自已盤了什！反勤漫薏」。這棣相峙了好多回之","box":[[97,623],[739,623],[739,640],[97,640]]},{"text":"後，那些急於這個問題上對我進行突破的提密員們，眼睛都變得紅","box":[[94,657],[741,655],[742,675],[94,677]]},{"text":"紅的像雨粒鬼火。","box":[[95,692],[265,692],[265,712],[95,712]]},{"text":"有一天來了-位穿軍服的提密員單獨對我提（通常來提蕃的都","box":[[139,728],[742,727],[743,745],[139,746]]},{"text":"是兩個人）。這個軍人高大而威猛，但他與其他提員不一樣，不逼","box":[[96,762],[741,761],[741,781],[96,782]]},{"text":"我交代[反動漫畫]的作案動機和作案過程，而是要我實事求是地把問","box":[[96,798],[740,797],[740,815],[96,816]]},{"text":"題说清楚。","box":[[96,833],[201,833],[201,853],[96,853]]},{"text":"「你一直坚持客觀上污辱了毛主席，但是没有主觀上的動機，」軍","box":[[140,868],[741,866],[742,886],[140,888]]},{"text":"人望著我说，「但這樣说是過不了關的。現在你好好回憶一下，你那個","box":[[96,903],[739,902],[739,922],[96,923]]},{"text":"圆案的究竟是什座？」","box":[[96,939],[326,938],[326,958],[96,959]]},{"text":"的究竟是什魔？」我被提密員這句突如其來的問話一下子搞槽","box":[[142,974],[740,972],[740,992],[142,995]]},{"text":"了，「不…....不是的個绞刑架？不是绞架還能是什？」","box":[[98,1010],[664,1008],[664,1029],[98,1030]]},{"text":"「绞架是這個樣子？」軍人直直地盯著我的眼睛反問道。","box":[[142,1045],[681,1044],[681,1064],[142,1065]]},{"text":"「那是什呢？」我上一片茫然。","box":[[142,1080],[463,1079],[463,1099],[142,1100]]},{"text":"「你自己回號子襄仔去想吧！」軍人合上案卷站起身來，「今天","box":[[142,1115],[742,1114],[743,1134],[142,1135]]},{"text":"就睿到這裹。","box":[[98,1151],[238,1151],[238,1171],[98,1171]]},{"text":"我魂不守舍地回到號子，一宿無眠，腦子裹一麻在飛旋。渐","box":[[141,1186],[744,1184],[745,1204],[141,1206]]},{"text":"大众图书馆http://dztsg.info","box":[[316,1297],[556,1297],[556,1317],[316,1317]]}],"dimensions":{"height":1346,"width":874}}