{"ocr_results":[{"text":"第二章少年心事當擎雲","box":[[89,68],[293,68],[293,85],[89,85]]},{"text":"37","box":[[715,71],[737,71],[737,89],[715,89]]},{"text":"極了，六十年代了，居然有如巴金的《家》中描述的大家族、大宅","box":[[89,126],[734,128],[734,148],[89,146]]},{"text":"院，居然還有「小姐！、「丫頭」，簡直是匪夷所思。我一面哈哈大笑，","box":[[89,161],[734,163],[734,184],[89,182]]},{"text":"一面續往下看她用優美的筆觸描述的那一幅幅江南水鄉的美麗圖","box":[[88,197],[733,198],[733,218],[88,217]]},{"text":"·無是「二十四橘明月夜，玉人何處教吹」的揚州、是「姑蘇城外","box":[[89,232],[733,233],[733,253],[89,252]]},{"text":"寒山寺，夜半鐘聲到客船」的蘇州、是那「山圍故國周遭在，潮打空","box":[[89,267],[732,268],[732,288],[89,287]]},{"text":"城寂寞回的南京城，還有那「煙龍寒水月箭沙，夜泊秦淮近酒家」的秦","box":[[89,302],[733,303],[733,323],[89,322]]},{"text":"淮河畔，都在她的筆下化作了美不勝收的文字，使我讀起來如醉如","box":[[89,337],[732,339],[732,359],[89,358]]},{"text":"凝。只可惜这十來封我視為極珍貴的游記體的書信，都在文革抄家时","box":[[90,375],[730,375],[730,392],[90,392]]},{"text":"燃飛灰减了。","box":[[90,411],[213,411],[213,428],[90,428]]},{"text":"新的學年開始了，施婷婷已是業班的學生，按规定不再任學","box":[[132,444],[732,446],[732,466],[131,464]]},{"text":"生會的工作，我們見面的機會也就很少。施婷婷業後考進了北京大","box":[[91,482],[731,482],[731,499],[91,499]]},{"text":"學中文系，離校前她在和我告别時说，希望一年後能在未名湖畔與我","box":[[89,515],[732,516],[732,536],[89,535]]},{"text":"重逢。但我還有一點自知之明，自知以我的語文水，在班上不過是","box":[[90,550],[731,551],[731,571],[90,570]]},{"text":"「猴子王」麗了，哪敢問津北大這樣的頂尖學府呢？而沉我也無意","box":[[90,585],[732,586],[732,606],[90,605]]},{"text":"涉足文科，為文科不過霉章摘句之類的雕蠢小技，「壮夫不為也」，","box":[[90,621],[727,622],[727,640],[90,639]]},{"text":"好男兒應在工程數理方面有一番建树，才能對國家有较大的獻。所","box":[[88,655],[732,656],[732,676],[88,675]]},{"text":"以到業時執意報考了工科院校·我的任語文老師洪家森、魏其巍","box":[[90,690],[732,692],[732,712],[90,710]]},{"text":"和吴，都對此抱遗憾，而我也覺得颇辜負了語文老師們的一份厚","box":[[91,728],[732,728],[732,745],[91,745]]},{"text":"望。","box":[[89,761],[133,761],[133,780],[89,780]]},{"text":"到這些老師們，我永遠都對他們满著敬意和感激之情。我自","box":[[133,796],[730,797],[730,817],[133,816]]},{"text":"恃語文方面成拔尖一點，没少過顽皮捣蛋·記得有一次洪老師在","box":[[89,831],[732,832],[732,852],[89,851]]},{"text":"我的一篇寫字習上批，字寫退步了。我居然就在老師的批語下","box":[[89,866],[731,868],[731,888],[89,886]]},{"text":"反批道：「何此也，殊不知吾前此乃臨帖督字，此次乃脱帖而書，焉","box":[[91,904],[732,904],[732,921],[91,921]]},{"text":"有不差之理敷？而日：退步了，夫是之主觀矣。呼，吾非發愤無","box":[[90,938],[732,939],[732,957],[90,956]]},{"text":"以谢天下！半文不白地強奪理了一番。但後來竟發現老師在我胡","box":[[90,972],[732,973],[732,993],[90,992]]},{"text":"之後寫道：你的批是對的，接受你的意見。我那時是大受感動，感","box":[[90,1008],[733,1010],[733,1028],[90,1027]]},{"text":"欺我們的老帥真正是虚饿若谷，喜如流，我是無地自容了。還有一","box":[[91,1046],[733,1046],[733,1063],[91,1063]]},{"text":"次我的一篇作文中，錯别学竟蓬十八個之多，魏老師批道，「錯字太","box":[[90,1080],[733,1081],[733,1099],[90,1098]]},{"text":"多了！而我居然恬不知耿地引鲁迅筆下那個孔乙已數茴香的話：","box":[[89,1114],[730,1115],[730,1135],[89,1134]]},{"text":"多乎哉？不多也！亚赫赫然就寫在老師的批語之下。老師後來知道","box":[[91,1150],[733,1151],[733,1169],[91,1168]]},{"text":"了，也没有怎责怪我，只是在一次作文講課上，提到有的同學錯","box":[[90,1184],[734,1185],[734,1205],[90,1204]]},{"text":"大众图书馆http://dztsg.infc","box":[[317,1298],[557,1298],[557,1318],[317,1318]]}],"dimensions":{"height":1346,"width":874}}