{"ocr_results":[{"text":"第三章大學，1966","box":[[108,68],[279,69],[279,89],[108,88]]},{"text":"53","box":[[737,72],[760,72],[760,90],[737,90]]},{"text":"重大的事情發生。但這個翼常重大的事情究竟是什事情，我們那時","box":[[109,128],[759,129],[759,149],[109,148]]},{"text":"還是猜不到的，除了傅播小道消息，也没有敢公開胡说八道。革命","box":[[109,163],[755,164],[755,184],[109,183]]},{"text":"的義，還是首先發在三家村這樣已經人人喊打的[反黑]身上最","box":[[111,199],[754,200],[754,218],[111,217]]},{"text":"保险。","box":[[109,233],[171,233],[171,254],[109,254]]},{"text":"但是吴晗、鄭拓、廖沫沙三人合寫的《三家村札記》也好，拓一","box":[[153,269],[755,270],[755,290],[153,289]]},{"text":"個人以馬南屯的筆名出的那本《燕山夜話》也好，我們那時的思想水","box":[[110,304],[753,305],[753,325],[110,324]]},{"text":"和政治水，要中讀出「反反社會主羲」的東西很困難。我們","box":[[109,338],[754,341],[754,361],[109,359]]},{"text":"只能通過姚文元們的《三家村》之類的批判文章，來解讀《三家村札","box":[[111,376],[753,377],[753,395],[111,394]]},{"text":"記》和《燕山夜話》中的「黑話」。例如「一個蛋的家當」這篇文章，说的","box":[[109,410],[753,411],[753,431],[109,430]]},{"text":"是刺1用空想代替现實的财迷本色，提出只有才能產生财富的","box":[[111,448],[752,448],[752,465],[111,465]]},{"text":"道理，應該没有什不對的嘛，但是姚文元看出了文章的背後，","box":[[109,481],[751,483],[751,502],[109,500]]},{"text":"是挖苦我們的社會主羲建設事業，是建立在只有一個蛋的家當的基","box":[[111,517],[753,519],[753,536],[111,534]]},{"text":"键之上」。又如「兩座的興魔」，是比较了同一地點兩座的與後，","box":[[110,552],[750,553],[750,571],[110,570]]},{"text":"對文物的保存問题發出了一些感欺；但是姚文元「獨具慧眼地看出","box":[[109,586],[754,587],[754,607],[109,606]]},{"text":"了文中所！興的那座朝，是暗示资本主羲制度，而所的那座，","box":[[113,624],[750,624],[750,641],[113,641]]},{"text":"是暗示社會主羲制度，文章是在煽勤與資無」。一篇谈陳緯和王耿","box":[[112,659],[754,659],[754,676],[112,676]]},{"text":"的案件」的文章，被说成是借古今，攻擎共產政治腐败，級门爭","box":[[110,692],[754,693],[754,713],[110,712]]},{"text":"大化；一篇「白開水最好喝」的科普小品，则是配合蘇修，挖苦我們","box":[[110,727],[753,728],[753,748],[110,747]]},{"text":"老百姓得只有水喝，「長髮的奇！，则是赤裸裸地鼓吹封建級資","box":[[111,765],[754,765],[754,782],[111,782]]},{"text":"產級腐朽没落的生活方式；而大話的故事和兩则外國寓言」，","box":[[111,800],[749,800],[749,817],[111,817]]},{"text":"则是公然大罐進是海口吹牛皮，「在實際的事物面前碰得頭破","box":[[112,835],[754,835],[754,852],[112,852]]},{"text":"血流」。至於一篇知識性的「三十六計」，據姚文元，三十六計，走","box":[[111,869],[754,870],[754,888],[111,887]]},{"text":"為上計，這是「三家村」见大勢不好，發出撤退的號令了。","box":[[110,904],[648,905],[648,923],[110,922]]},{"text":"姚文元不愧是個嘎覺敏的刀筆吏，用穿鳌附會的方法，把「三","box":[[155,941],[754,941],[754,958],[155,958]]},{"text":"蒙村的文章韵析一番，便將部拓、吴晗等[反分子的[反動面目1，","box":[[111,976],[750,976],[750,993],[111,993]]},{"text":"-","box":[[29,987],[37,987],[37,1000],[29,1000]]},{"text":"完全暴露在了光天化日之下。按照姚文元定下的調調，我們然都没","box":[[111,1010],[754,1012],[754,1030],[111,1029]]},{"text":"有讀過拓吴晗寫的那些夜話和札記的原文，照樣對其大批没商","box":[[111,1047],[755,1047],[755,1064],[111,1064]]},{"text":"量。我也在班上召開的批判會上，慷慨激昂地念了一首鼓噶，春草","box":[[111,1083],[756,1083],[756,1100],[111,1100]]},{"text":"生，狼子野心三家村·...的打油詩來凑熱闹。自己横極不，在","box":[[111,1118],[756,1118],[756,1135],[111,1135]]},{"text":"一次團組織生活中，批不爱開口的阿玲不棱極在批判會上發言，哪","box":[[112,1153],[756,1153],[756,1170],[112,1170]]},{"text":"像個共青團員？」阿玲突然就哭了，雙手蒙著跑出了教室。我意識到","box":[[110,1186],[756,1187],[756,1207],[110,1206]]},{"text":"大众图书馆http://dztsg.info","box":[[317,1298],[557,1298],[557,1318],[317,1318]]}],"dimensions":{"height":1346,"width":874}}