{"ocr_results":[{"text":"184■毛澤東的金棍子：姚文元與「文革」（下）","box":[[109,83],[467,83],[467,100],[109,100]]},{"text":"方法統一的。雲南搞得相當凶就是了。","box":[[110,178],[497,179],[497,199],[110,198]]},{"text":"自然科學和哲學一黛校寫。","box":[[155,217],[430,217],[430,235],[155,235]]},{"text":"科學院内最大危是派性，忘記了列寧過哲學上的黛派门争，","box":[[154,254],[788,254],[788,271],[154,271]]},{"text":"二千年就是门爭著的雨個黛派。學上也有派，唯物主義和唯心主義。","box":[[112,291],[781,291],[781,308],[112,308]]},{"text":"内蒙還可以寫，吉林請他們寫也可以。山東、安徽、北大也打招","box":[[154,328],[795,328],[795,345],[154,345]]},{"text":"呼，重新修改。批智育第一，可以羚人民日報。有的熟悉的同志，也可","box":[[110,366],[793,366],[793,380],[110,380]]},{"text":"以，文章的面要注意平衡。清華北大繁急時可以我們。","box":[[111,401],[670,401],[670,419],[111,419]]},{"text":"「群」一篇。講群累是真正的英雄。藩陽機電學院二張大字報，","box":[[157,434],[792,436],[792,459],[156,457]]},{"text":"第一張大學生和工人·劃等號，，這個點很值得注意。他們也是工","box":[[111,475],[795,475],[795,492],[111,492]]},{"text":"震兵学員，提這個口號是什意思呢？要做工人貴族。工人中有一部分","box":[[111,513],[793,513],[793,530],[111,530]]},{"text":"人不和普通工人劃等號，要做貴族·英國工黛不和工人劃等號，但和","box":[[111,549],[795,549],[795,566],[111,566]]},{"text":"資產劃等號。美國、產也是這，也是和資產劃等號。","box":[[111,586],[790,586],[790,604],[111,604]]},{"text":"上人意族，不是工人赌被，是餐産赌毅在工人内部的代表。普通工人","box":[[112,625],[787,625],[787,639],[112,639]]},{"text":"震民、每天都在進步，主席講過，人人都要改造，工人楷也要改造，","box":[[111,659],[790,659],[790,676],[111,676]]},{"text":"每人都要改造。要做工人貴族的人放在工人之外。群累是真正的英雄，","box":[[111,697],[790,697],[790,714],[111,714]]},{"text":"我們自已往往是幼稚可笑的。實践觀點看，往往下毅水高於上","box":[[111,734],[795,734],[795,751],[111,751]]},{"text":"毅，群農高於领導，领導不如普通劈動者·领導常常脱離群累，没有實","box":[[110,771],[794,771],[794,788],[110,788]]},{"text":"經驗·導只有糙了群累經驗，才能進步，才能带群累前進，脱離","box":[[111,809],[794,809],[794,823],[111,823]]},{"text":"群累就一事無成。我們有些同志往往為比群高明。毛主席教導我","box":[[111,844],[795,844],[795,862],[111,862]]},{"text":"們，要做群累的小學生，要以普通劈動者姿態出現。智慧和力量在十","box":[[111,883],[794,883],[794,897],[111,897]]},{"text":"萬离萬普通务動者之中·领導部就是要向普通穷勤者学背，結經","box":[[112,920],[794,920],[794,934],[112,934]]},{"text":"才能前進。我们也不主張無政府主義。老中青都要打招呼，青也要找","box":[[110,955],[794,955],[794,972],[110,972]]},{"text":"好的，不要大富這種人，他們看不起群累，看不起工人，打工宣隧，","box":[[111,992],[789,992],[789,1009],[111,1009]]},{"text":"杭州還有翁森。這一點如何講深刻點。","box":[[112,1030],[495,1030],[495,1045],[112,1045]]},{"text":"毛中主席要各地寫報告，我們的材料是你們那狸來的，要各","box":[[154,1066],[794,1066],[794,1083],[154,1083]]},{"text":"殺定期寫報告。《委會的工作方法》講到，中央领導之所以正確，主","box":[[109,1100],[796,1101],[796,1121],[109,1120]]},{"text":"要是由於踪合了各地供的材料、報告和正確的意見，如果各地不来材","box":[[112,1140],[794,1140],[794,1157],[112,1157]]},{"text":"料，不提意見，中央很正確地發號施令。领導材料群累中來。文化","box":[[110,1177],[794,1177],[794,1194],[110,1194]]},{"text":"大革命以來，（主席）總結好多好的經驗，批了好多文章·如革命委員","box":[[110,1211],[794,1212],[794,1231],[110,1230]]}],"dimensions":{"height":1359,"width":945}}