{"ocr_results":[{"text":"030■毛澤東的金棍子：姚文元舆「文革」（下）","box":[[110,84],[467,84],[467,101],[110,101]]},{"text":"黑手時，理）你們打電話回去查一下，北京還有什人在浙","box":[[177,181],[794,181],[794,198],[177,198]]},{"text":"江，如果還有，很快報告我們，我們通令他們回乘，他們這時候","box":[[176,217],[794,217],[794,235],[176,235]]},{"text":"再去串，就是倒忙了。","box":[[176,254],[430,253],[430,271],[176,272]]},{"text":"（當省匯報到有的學生到公安串時，理）公、","box":[[229,291],[789,291],[789,308],[229,308]]},{"text":"、法的粗織不充許舆外面瞬繁，只許在内部搞揭發，不能到社","box":[[176,329],[794,329],[794,346],[176,346]]},{"text":"會上去串。因為它是專政機，一手拿檐，一手搞群累連動就","box":[[177,365],[795,365],[795,382],[177,382]]},{"text":"要搞腻了。","box":[[176,400],[279,400],[279,421],[176,421]]},{"text":"（當瞭解到省軍區幹部來北京學智，没通知紅暴参加時，","box":[[228,439],[795,439],[795,456],[228,456]]},{"text":"理）那是個缺點，我們也没有注意這一點。","box":[[176,474],[606,475],[606,493],[176,492]]},{"text":"紅暴要拉起大旗，搞全省組織，跟你們闹對立，那是不對","box":[[222,513],[794,513],[794,530],[222,530]]},{"text":"的。現在就是要按照主席的最新指示，门私批修，各自多做自我","box":[[174,547],[796,548],[796,568],[174,567]]},{"text":"批。紅暴是犯過錯的老造反派，紅暴那狸有那算，基層有","box":[[177,586],[794,586],[794,604],[177,604]]},{"text":"的就在基層合，當然要助，批辞他們，明他們識錯。","box":[[176,623],[790,623],[790,640],[176,640]]},{"text":"工代會，紅代會都充許他們参加，充許他們承錯，實現","box":[[177,660],[795,660],[795,677],[177,677]]},{"text":"合。省、市革命委員會要有他們的代表。地縣原來有紅暴的，或","box":[[177,697],[795,697],[795,714],[177,714]]},{"text":"者有觀點與紅暴相同的組織的，在他們承錯讨之後可在地","box":[[177,734],[795,734],[795,751],[177,751]]},{"text":"縣舆他們合，當然温州、金華、肖山、暨等是另外性質。就","box":[[177,771],[795,771],[795,788],[177,788]]},{"text":"是這些地方組織，在承這些後，也充許他們回來。温州造","box":[[177,808],[795,808],[795,825],[177,825]]},{"text":"反派在政策上掌握不好，不大符合主席的教育，爭取，分化的方","box":[[177,844],[794,844],[794,862],[177,862]]},{"text":"針，要有他们自己出壤人，走資派。工總司没有做好這工作，","box":[[174,881],[790,880],[790,897],[174,898]]},{"text":"現在還有白人在山上，武器在他們手裡，逼理還有些是穷勤人","box":[[177,920],[792,920],[792,934],[177,934]]},{"text":"民。工司有些口號提得不當，非要叫老保，要他們投降。人民","box":[[176,955],[795,955],[795,972],[176,972]]},{"text":"大會堂（指北京）有個工作人員，全家是工司，就是一個哥哥","box":[[176,992],[795,992],[795,1009],[176,1009]]},{"text":"在温瞬，大家都批他，但他他們要我投降我就不服氣，我","box":[[177,1029],[795,1029],[795,1047],[177,1047]]},{"text":"是想捍衛毛主席的革命路的，不過被他们（指走資派）欺骗走","box":[[177,1066],[794,1066],[794,1083],[177,1083]]},{"text":"錯路了·要把黑手，走資派，壤頭頭和廣大群區别崩來，因為","box":[[177,1103],[794,1103],[794,1120],[177,1120]]},{"text":"他是走資派操利用的。温瞬有點白萬雄師的棣子，你們是多","box":[[177,1140],[794,1140],[794,1157],[177,1157]]},{"text":"數派，在全省也是多數。占侵勢了。現在已開了工代會，紅代會","box":[[177,1177],[794,1177],[794,1194],[177,1194]]},{"text":"建立革委會更是多數。正是這樣，更要高姿。（姚文元同志插","box":[[176,1213],[795,1213],[795,1231],[176,1231]]}],"dimensions":{"height":1359,"width":945}}