{"ocr_results":[{"text":"五号楊承效还在那里拉队伍，还在那里发“宣言”，临分裂，这是苹命吗？！揚承效","box":[[307,325],[1870,324],[1870,370],[307,372]]},{"text":"同志，你这个人我过去是保过你的，是不是保过？那时你是造卫、王、王的反，选","box":[[310,391],[1864,391],[1864,432],[310,432]]},{"text":"鲁篇的反，，那时我們保过你。因为当时另一浪的矛头是对准革委会的，收保你是从大","box":[[306,454],[1868,454],[1868,495],[306,495]]},{"text":"局着想，为了雄护山西的苹命委员会，为了山西的苹命間题。现在是另外一回事，要","box":[[310,514],[1870,514],[1870,556],[310,556]]},{"text":"狠狠批部你。前年十二月你从东北四米后，我肴你就没有做过一件好事！你要好好妆","box":[[308,580],[1869,580],[1869,617],[308,617]]},{"text":"查检查，你现在官做大了，是省苹命委员会的常委。北京卫戌区反映，你在北京有好","box":[[306,642],[1868,641],[1868,679],[306,681]]},{"text":"多楊公馆，杨承公馆。（杨：没有）你不要就这个站，你的恍况我都知道！","box":[[308,703],[1734,704],[1734,746],[308,745]]},{"text":"总理：任何单位来的人，只能在中央指定的学习班卫学习，你（指杨承效）自己","box":[[392,763],[1864,761],[1864,798],[392,800]]},{"text":"不能到处搞联赂站，搞联絡点，开旅馆，那不行！","box":[[311,822],[1235,825],[1235,863],[311,860]]},{"text":"康生同志：你（指杨承效）花了国家多少，自己检查查。有些工人同志都是","box":[[394,875],[1864,878],[1864,918],[393,916]]},{"text":"很好的，叫你給带坏了。在座的姚恩泉同志，你多火？（二十九岁）二十九了。王国","box":[[312,943],[1865,943],[1865,980],[312,980]]},{"text":"太同志多大了？（王：二十儿岁）也二十九岁。背年人都叫你带坏了，你要很好地检","box":[[310,1004],[1863,1004],[1863,1045],[310,1045]]},{"text":"查一下。（王国太：有些事情我們在一起也是斗私丶批修，互相批评的）要白己在","box":[[310,1070],[1861,1068],[1861,1106],[310,1108]]},{"text":"众中很好地检查，看看怎么样。我不是说另外一派没缺点，你們自己的缺点、要","box":[[311,1131],[1861,1131],[1861,1168],[311,1168]]},{"text":"作自我批评。你們过去“紅总站”在山西力量是大的，比“兵团”力量大嘛！你們应","box":[[310,1190],[1863,1189],[1863,1227],[310,1228]]},{"text":"当带个头。（姚恩泉：这次联合我們早就达成了协，我們原来十七个常委，落选了","box":[[316,1252],[1856,1250],[1856,1289],[316,1290]]},{"text":"七个）杨承效带头发过“宣言”嘛！（杨承效：五号发的“宣言”，六号刘格平同志","box":[[312,1311],[1859,1311],[1859,1353],[312,1353]]},{"text":"就批评了）那个批评是不痛不痒的，这个我都知道，刘格平敢批评你！你现在是老子","box":[[311,1377],[1863,1377],[1863,1418],[311,1418]]},{"text":"天下第一，敢批评你。所以大家还是要作自我批部，检查自己，人家的缺点、误","box":[[310,1444],[1858,1442],[1858,1479],[310,1481]]},{"text":"让人家自己。陈广仁同志，你們也要作自我批评。（陈：山西没搞好苹命我們有贵","box":[[308,1506],[1856,1504],[1856,1541],[308,1543]]},{"text":"任，十三冶没搞好苹命，我們也有贵任）十三冶金建設公司，我看现在叫破坏公司，","box":[[308,1568],[1847,1566],[1847,1606],[308,1609]]},{"text":"破坏建設。你們（对承效）在东北时是在哪里？（答：在富拉尔基）那时搞得很好","box":[[313,1632],[1856,1632],[1856,1665],[313,1665]]},{"text":"嘛！你們現在闲成这个样子！恰恰是在八屆扩大的十二中全会以后，在一月份你們还","box":[[311,1694],[1856,1691],[1856,1729],[311,1732]]},{"text":"拉队伍出来。（王国太：批判“二月逊流”的大会我們和部队合着开的）一起批判","box":[[311,1753],[1859,1754],[1859,1792],[311,1791]]},{"text":"刘、陈、刘，准备批斗刘志兰，他们没有給，还说我們打若批判“二月逆流”的幌子","box":[[311,1815],[1861,1815],[1861,1852],[311,1852]]},{"text":"开黑会）你們联合起来批斗不就好了？（王：有人不让批判，说刘、陈、刘要结","box":[[310,1879],[1855,1878],[1855,1915],[310,1916]]},{"text":"合，什么白毛女要翻身）刘志兰的问题中火老早就知道，中央批部了。为了一个刘志","box":[[308,1938],[1856,1940],[1856,1982],[308,1980]]},{"text":"兰問题就可以发“宣言”，发“声明”，就破坏大局，不联合了吗？！没有大联合怎","box":[[316,2005],[1855,2005],[1855,2042],[316,2042]]},{"text":"么批判呢？（王：大联合問题我准备谈一）不要了，回去时要好好帮助他們实现","box":[[311,2063],[1858,2065],[1858,2106],[311,2103]]},{"text":"大联合。你們不要在这里打电話，搞控了。（王国太表态）你别了，好站我听了","box":[[307,2121],[1856,2122],[1856,2171],[307,2170]]},{"text":"好多了，現在要看实际。","box":[[309,2191],[754,2193],[754,2231],[308,2229]]},{"text":"我們没有多少話了。如果你們再不执行毛主席的无产阶级苹命路，全国二十","box":[[396,2255],[1856,2254],[1856,2292],[396,2293]]},{"text":"八个省、市的工人要造你們的反了！赞成？（热烈鼓学）（口号：毛主席的书！","box":[[312,2309],[1853,2313],[1853,2358],[312,2354]]},{"text":"听毛主席的話！紧跟毛主席的律大战略部署！坚决摘掉山西的落后帽子！毛主席万","box":[[311,2378],[1855,2378],[1855,2418],[311,2418]]},{"text":"岁！方岁！万万岁！)","box":[[315,2439],[729,2439],[729,2476],[315,2476]]},{"text":"康生同志：没有把握的先不要回去，带着派性回去更危险。","box":[[403,2506],[1462,2506],[1462,2539],[403,2539]]},{"text":"总理：现在請江青同志給我們讲几句話。","box":[[399,2561],[1132,2565],[1132,2607],[398,2603]]},{"text":"~","box":[[405,2626],[429,2626],[429,2649],[405,2649]]},{"text":"8","box":[[398,2651],[435,2651],[435,2699],[398,2699]]}],"dimensions":{"height":3072,"width":2171}}