{"ocr_results":[{"text":"1967171","box":[[753,80],[837,83],[836,103],[752,100]]},{"text":"先锋作用。這個火是毛主席點起來的。","box":[[150,181],[512,181],[512,198],[150,198]]},{"text":"目前已到了奪權的時候了，是不是全部奪權？都是在需要的地方向","box":[[193,217],[832,217],[832,235],[193,235]]},{"text":"内一小撮走資本主義道路當權派奪權。","box":[[149,254],[536,254],[536,271],[149,271]]},{"text":"人家都起來了，但中學如果不做到這一點，中學运動就有可能走過","box":[[192,291],[832,291],[832,308],[192,308]]},{"text":"場·如果不是課，就不能將無產隋殺文化大革命進行到底！馥課也是","box":[[149,329],[833,329],[833,346],[149,346]]},{"text":"把中學文化革命推向前進，从社會到學校不能是消極的，應看到革","box":[[150,365],[833,365],[833,382],[150,382]]},{"text":"命在前進，中央的指示是適應新的情况的·紅衛兵本身也是這樣，紅備","box":[[151,401],[832,401],[832,419],[151,419]]},{"text":"兵翘織也是在不前進的。回校整，思想上也有好多問题要解决的。","box":[[150,439],[828,439],[828,456],[150,456]]},{"text":"到社會上去是好的，但社鲁上也有嘴毅门争，也會沾染了許多不好的東","box":[[151,477],[832,477],[832,491],[151,491]]},{"text":"西，就像無政府主義、自由主義·…事倩總是那樣一分為二的·.·...·在","box":[[147,511],[835,510],[835,530],[147,531]]},{"text":"一定的歷史轉變關頭，新生力量是一定不的出來的，我们應該向東","box":[[149,549],[833,549],[833,566],[149,566]]},{"text":"方紅门隧學習，十七、八的小將做了好事都可以學習。","box":[[151,586],[710,586],[710,604],[151,604]]},{"text":"到了新的睦史脂段就要求我們找到新的翘識形式，是不是這裡找","box":[[194,625],[832,625],[832,639],[194,639]]},{"text":"到經，要在破私立公的前提下在組織上提供一個好經驗，學校的紅備","box":[[150,660],[832,660],[832,677],[150,677]]},{"text":"兵組織究竟怎搞。","box":[[151,697],[339,697],[339,714],[151,714]]},{"text":"馥課是在更深人的段出現的新生事物。","box":[[193,734],[577,734],[577,751],[193,751]]},{"text":"上海的學生要適應新的形勢，以後還要批判資產毅反動路線，改","box":[[195,771],[834,771],[834,788],[195,788]]},{"text":"革教育制度。革命還有得要搞了。課不是消極的把人叫回來，主要是","box":[[150,806],[833,807],[833,825],[150,824]]},{"text":"把革命推向前進·把文化革命搞深搞透，對師生的思想改造，對教學制","box":[[150,844],[833,844],[833,862],[150,862]]},{"text":"度的改革非常重要。回校後封社會的情况不警是完全隔绝的。馥踝闹革","box":[[151,883],[831,883],[831,897],[151,897]]},{"text":"命怎樣搞好，這裡會出新的典型，革命的將。","box":[[151,918],[601,918],[601,935],[151,935]]},{"text":"把大家的革命幹劲發動起來，革命的教學是可以解决的。","box":[[193,955],[729,955],[729,972],[193,972]]},{"text":"有成續的單位，都希望他們前進，落後的單位，都希望他們程上","box":[[192,992],[834,992],[834,1009],[192,1009]]},{"text":"去。紅備兵中有一批是擎持到底的，但也有囊花一現的人物，在關键的","box":[[151,1030],[831,1030],[831,1045],[151,1045]]},{"text":"時刻走到歷史的反面，但這也没有什，還可以回來。","box":[[149,1066],[665,1066],[665,1083],[149,1083]]},{"text":"有人假冒紅備兵的名字，乾了不符合毛澤東思想的事，這方面還有","box":[[192,1102],[832,1102],[832,1119],[192,1119]]},{"text":"相當尖的隋級门爭。","box":[[148,1138],[361,1137],[361,1157],[148,1158]]},{"text":"對「聯動」的门爭，革命的紅衛兵在思想上識透，打擎一小撮頭","box":[[190,1175],[834,1175],[834,1195],[190,1195]]},{"text":"頭。這是中國楷毅门争的一個組成部分，是兩條路線在中國的反映，是","box":[[150,1213],[832,1213],[832,1231],[150,1231]]}],"dimensions":{"height":1359,"width":945}}