{"ocr_results":[{"text":"190■毛澤東的金棍子：姚文元舆「文革」（上）","box":[[110,84],[467,84],[467,101],[110,101]]},{"text":"些地方實現革命的大聯合已經有些很好的經驗，就是實現革命的大聯合","box":[[110,178],[795,179],[795,199],[110,198]]},{"text":"要通過门争，通過整風，通過學習·通過共同對蔽门爭，團結起來，實","box":[[112,217],[795,217],[795,235],[112,235]]},{"text":"現了革命的大麟合·通過開门整風，大家在毛王席思想基上瞬合起","box":[[111,256],[793,256],[793,270],[111,270]]},{"text":"乘，實現了革命的大合·通過學習，明罐了门争的大方向，在批判、","box":[[111,291],[790,291],[790,308],[111,308]]},{"text":"控資產隋毅反勤路基上，實現了革命的大瞬合。有了共同的目","box":[[110,329],[793,329],[793,346],[110,346]]},{"text":"標，共同的識，在毛澤東思想的原则基上，沿著毛主席的無產","box":[[111,365],[794,365],[794,382],[111,382]]},{"text":"革命路線指出的方向，廣大的無產楷革命派，革命造反派，應合","box":[[111,401],[794,401],[794,419],[111,419]]},{"text":"起來，團結起來。","box":[[111,439],[279,439],[279,456],[111,456]]},{"text":"我們有的同志，忘掉了還有蔽人，忘掉了資本主義勢力還千方百計","box":[[154,476],[793,476],[793,493],[154,493]]},{"text":"的想復辟，忘掉了我們還有革命的重的任務，還要反復辟，還要搞","box":[[108,510],[795,511],[795,531],[108,530]]},{"text":"门、批、改，忘掉了這一些，就不想搞革命的大合了，心想的圍","box":[[110,549],[794,549],[794,566],[110,566]]},{"text":"很小，只有我這個團體怎樣、怎樣·林彪同志曾經：要去掉偏限性。","box":[[111,586],[791,586],[791,604],[111,604]]},{"text":"固人王羲是一種偏限性，小團體王羲也是一種偏限性，只有站到無產陷","box":[[112,625],[793,625],[793,639],[112,639]]},{"text":"的立場上來，才能去掉這種偏限性·因為無產級目標遠大，要到全","box":[[111,660],[794,660],[794,677],[111,677]]},{"text":"世界實現共產主義，站在無產毅立場上，就能看到门争的全域，去掉","box":[[112,697],[794,697],[794,714],[112,714]]},{"text":"限性。","box":[[111,734],[192,734],[192,751],[111,751]]},{"text":"任何一個正確的口號，都可能被曲解。革命的大聯合剛提出不久，","box":[[154,769],[789,769],[789,790],[154,790]]},{"text":"有的人就成「要解散一切革命組織」，「這是要把所有的革命造反組","box":[[111,806],[794,806],[794,826],[111,826]]},{"text":"織都取消，和群合供」等等。引起了一些思想混。我們革命的大","box":[[111,844],[795,844],[795,862],[111,862]]},{"text":"瞬合，是組織形式上的改變和整，不是不要革命組織，經過整以","box":[[110,882],[794,882],[794,899],[110,899]]},{"text":"後，革命造反派的組織，無產革命派的組織，革命的紅衛兵，不但","box":[[111,918],[793,918],[793,935],[111,935]]},{"text":"不能削弱，而要大大加强政治上的無產隋毅的先進性、戴门性。很明","box":[[111,956],[794,956],[794,973],[111,973]]},{"text":"，現在有一些地方實現了大瞬合不是造反派還存在？有的是解，","box":[[111,992],[791,992],[791,1009],[111,1009]]},{"text":"有的是一些人在挑動，一些别有用心的人，不想搞大合，就挑動·你","box":[[112,1029],[795,1029],[795,1047],[112,1047]]},{"text":"不要搞了，搞了以後什組織都没有了」。我們要識破。革命的大","box":[[110,1065],[795,1065],[795,1085],[110,1085]]},{"text":"合，不是取消主羲，不是·合二而一」，不是把革命派和保守派合佛","box":[[112,1103],[794,1103],[794,1120],[112,1120]]},{"text":"起來。","box":[[110,1139],[170,1139],[170,1157],[110,1157]]},{"text":"在中央指出的種種錯倾向當中，反革命經湾主義的危害性，我們","box":[[155,1177],[795,1177],[795,1194],[155,1194]]},{"text":"在一月革命過程中有了深刻的識。《文匯報》有一篇·風頭主義」社","box":[[112,1213],[795,1213],[795,1231],[112,1231]]}],"dimensions":{"height":1359,"width":945}}