{"ocr_results":[{"text":"1967249","box":[[753,80],[836,83],[835,103],[752,100]]},{"text":"我們念《罐話》發表二十五周年，首先要真地學智毛主席這篇","box":[[193,181],[833,181],[833,198],[193,198]]},{"text":"偉大著作和其他關於文化革命的偉大著作，當作我們進行大批判的最重","box":[[150,217],[834,217],[834,235],[150,235]]},{"text":"要的门武器，政治上、思想上、理上、組織上澈底摧毁反革命修","box":[[150,254],[833,254],[833,271],[150,271]]},{"text":"正主義文藝黑線所占據著的陣地，需清它們的毒素，弄清它们的一切地","box":[[150,291],[832,291],[832,308],[150,308]]},{"text":"下活勤，把领導權真正奪到無産楷毅革命派手中來，亚且進一步澈底批","box":[[151,330],[832,330],[832,344],[151,344]]},{"text":"臭文藝黑線的總後台一一内最大的一小走資本主義道路的当權派，","box":[[149,364],[828,363],[828,381],[149,382]]},{"text":"把革命的大批判運動推向一個新的高潮。","box":[[150,401],[536,401],[536,419],[150,419]]},{"text":"馬克思列寧主義、毛澤東思想是革命的、批判的學，它來就是","box":[[193,439],[833,439],[833,456],[193,456]]},{"text":"在同：左，右随機會王羲和形形色色資產隋毅反動思潮的门爭中，開麟","box":[[151,477],[832,477],[832,491],[151,491]]},{"text":"自己的前進的道路的。门爭中來學智毛澤東思想，才能真正掌握毛澤","box":[[151,513],[833,513],[833,530],[151,530]]},{"text":"東思想的革命的囊魂。只有掌握了毛澤東思想，才能予資產反動","box":[[150,549],[833,549],[833,566],[150,566]]},{"text":"路線以致命的打墅。我們無產隋級文化大革命的一切勝利，歸根到底，","box":[[149,585],[830,584],[830,603],[149,604]]},{"text":"都是毛澤東思想、以毛主席為代表的無産隋毅革命路裸對於餐産隋毅反","box":[[151,625],[832,625],[832,639],[151,639]]},{"text":"勤思想和資產級反動路線的勝利。已經處在掌權地位的上海無產楷毅","box":[[150,660],[832,660],[832,677],[150,677]]},{"text":"革命派的同志們，一定要把學智、掌握、運用毛澤東思想，放到高於一","box":[[150,697],[833,697],[833,714],[150,714]]},{"text":"切、大於一切、先於一切、重於一切的位置上，念念不忘，天天不停，","box":[[149,733],[827,732],[827,749],[149,750]]},{"text":"切不可被日常的繁忙的事務掉了學智的時間。","box":[[151,771],[600,771],[600,788],[151,788]]},{"text":"思想的陣地必须用思想的武器去估领。靠拳頭，靠打砸，是不能","box":[[194,808],[833,808],[833,825],[194,825]]},{"text":"把資產級思想搞掉的。被資產思想占领著的地方，必须用毛澤東","box":[[149,844],[833,844],[833,862],[149,862]]},{"text":"思想去批判，去戴门，才能把陣地奪取到無產隋毅手中。被餐產隋毅反","box":[[151,883],[832,883],[832,897],[151,897]]},{"text":"動路線毒害、欺、蒙蔽的群，只有用毛澤東思想去向他們進行思想","box":[[150,918],[834,918],[834,935],[150,935]]},{"text":"教育，才能使他們覺醒過來，自覺地清除頭腦狸的錯思想，回到毛主","box":[[150,955],[832,955],[832,972],[150,972]]},{"text":"席的路線上來。能不能把思想上的门争搞好，這是關係到我們能不","box":[[150,992],[833,992],[833,1009],[150,1009]]},{"text":"能把這場無產毅文化大革命進行到底的問题。","box":[[151,1030],[599,1030],[599,1045],[151,1045]]},{"text":"應當看到，在思想、文化领域中的資產毅的反勤思想及其代表人","box":[[193,1066],[834,1066],[834,1083],[193,1083]]},{"text":"物，是很旗强的。剥削隋毅的傅影響，售的背惯努力，要經過很長的","box":[[150,1104],[832,1104],[832,1118],[150,1118]]},{"text":"史時期，才能逐步消除。挖出了資產隋毅代表人物，亚不等於赢清了","box":[[150,1140],[832,1140],[832,1157],[150,1157]]},{"text":"他們的影響；挖掉了售的資產代表人物，還會產生新的資產毅代","box":[[150,1177],[833,1177],[833,1194],[150,1194]]},{"text":"表人物。毛主席在最近又一次重複地提醒我們：「現在的文化大革命，","box":[[148,1210],[830,1211],[830,1232],[148,1231]]}],"dimensions":{"height":1359,"width":945}}