{"ocr_results":[{"text":"336■毛澤東的金棍子：姚文元與「文革」（上）","box":[[110,83],[467,83],[467,100],[110,100]]},{"text":"17.China'sCountryside:AVastSchoolforHerYouth.Peking:Foreign","box":[[108,178],[795,179],[795,202],[108,201]]},{"text":"LanguagesPress,1976.","box":[[136,215],[341,216],[341,238],[136,237]]},{"text":"18.[美]安德鲁，《張春橘和上海的一月革命》，美國密西根大學出版","box":[[108,250],[797,252],[797,275],[108,273]]},{"text":"社，1978年。","box":[[136,289],[263,287],[263,308],[136,311]]},{"text":"19.齊辛，《四人事件探索》，香港：七十年代雜社，1978年。","box":[[110,327],[742,327],[742,347],[110,347]]},{"text":"20.Lee,HongYong.ThePoliticsof theChineseCulturalRevolution.","box":[[108,364],[794,364],[794,387],[108,387]]},{"text":"Berkeley:UniversityofCaliforniaPress,1978.","box":[[137,401],[547,401],[547,422],[137,422]]},{"text":"21.[日]佐藤慎一郎，《毛澤東「萬崴」和「萬碎」》’大潦書店，","box":[[108,437],[791,436],[791,457],[108,458]]},{"text":"1979年。","box":[[139,475],[221,475],[221,493],[139,493]]},{"text":"22.杨释，《韩校六記》，生活、讀書、新知三出版社，1981年。","box":[[109,511],[742,511],[742,531],[109,531]]},{"text":"23.《歷史的蕃判》辑組，《歷史的蕃判》，群出版社，1981年。","box":[[109,548],[787,548],[787,568],[109,568]]},{"text":"24.王希哲，《毛澤東舆文化大革命》，香港：時代出版社，1981年。","box":[[110,585],[763,585],[763,603],[110,603]]},{"text":"25.王際真，《雨作家舆文化革命：老舍和陳若曦》，中央大學，","box":[[109,622],[788,622],[788,642],[109,642]]},{"text":"1981。","box":[[138,659],[197,659],[197,677],[138,677]]},{"text":"26.Ditttner,Lowell.“Ethicsandrhetoricof theChineseCulturalRevolution.\"","box":[[109,696],[795,696],[795,716],[109,716]]},{"text":"StudiesinChineseTerminology,No.19.Berkeley:CenterforChinese","box":[[137,732],[795,733],[795,754],[137,753]]},{"text":"Studies,InstituteofEastAsianStudies,UniversityofCalifornia,1981.","box":[[138,771],[756,771],[756,791],[138,791]]},{"text":"27.Rosen,Stanley.TheRoleofSent-downYouthintheChineseCultural","box":[[109,806],[797,807],[797,828],[109,827]]},{"text":"Revolution:Case of Guangzhou.Berkeley:Center for Chinese Studies,","box":[[137,843],[795,843],[795,867],[137,867]]},{"text":"UniversityofCalifornia,1981.","box":[[137,881],[404,881],[404,901],[137,901]]},{"text":"28.陳若曦，《中國文化革命倫理和語言》，加大柏克莱，1982。","box":[[110,917],[720,917],[720,937],[110,937]]},{"text":"29.Rosen,Stanley.Red GuardFactionalismandtheCulturalRevolutionin","box":[[108,951],[796,954],[796,977],[108,975]]},{"text":"Guangzhou.WestviewReplicaEdition.Boulder:WestviewPress,1982.","box":[[138,991],[764,990],[764,1011],[138,1012]]},{"text":"30.MacFarquhar,Roderick.The Great Leap Forward,1958-1960: The","box":[[109,1027],[796,1027],[796,1051],[109,1051]]},{"text":"OriginsoftheCulturalRevolution,V2.StudiesoftheEastAsian","box":[[138,1065],[796,1065],[796,1088],[138,1088]]},{"text":"Institute.TheRoyalInstituteofInternationalAffairs,theEastAsian","box":[[137,1102],[796,1102],[796,1122],[137,1122]]},{"text":"InstituteofColumbiaUniversity,&theResearchInstituteonInternational","box":[[137,1139],[796,1139],[796,1159],[137,1159]]},{"text":"Change of ColumbiaUniversity.NewYork:ColumbiaUniversityPress,","box":[[136,1174],[795,1176],[795,1199],[136,1197]]},{"text":"1983.","box":[[138,1213],[184,1213],[184,1232],[138,1232]]}],"dimensions":{"height":1359,"width":945}}