{"ocr_results":[{"text":"342■毛澤東的金棍子：姚文元與「文革」（上）","box":[[108,82],[468,81],[468,101],[108,102]]},{"text":"1995年。","box":[[147,178],[229,178],[229,199],[147,199]]},{"text":"115.戴家枋，《樣板的風風雨雨一樣板、江青及内幕》，知識出","box":[[109,212],[794,213],[794,237],[109,236]]},{"text":"版社1995年。","box":[[147,252],[273,252],[273,273],[147,273]]},{"text":"116.安建設，《周恩來的最後崴月（1966一1976）》（增訂本），中央","box":[[109,288],[794,290],[794,310],[109,308]]},{"text":"文獻出版社，1995年。","box":[[147,326],[360,326],[360,346],[147,346]]},{"text":"117.汪東林，《十年風暴乍起時的政協知名人士》，中國文史出版社，","box":[[109,362],[788,363],[788,383],[109,382]]},{"text":"1995年。","box":[[148,399],[230,399],[230,421],[148,421]]},{"text":"118.于光遠，《文革中的我》，上海遠東出版社，1995年。","box":[[111,437],[665,437],[665,457],[111,457]]},{"text":"119.定宜莊，劉小萌、史衛民、何属，《中國知青事典》，四川人民出","box":[[110,472],[793,474],[793,494],[110,492]]},{"text":"版社，1995年。","box":[[147,511],[294,511],[294,531],[147,531]]},{"text":"120.Wang,Shaoguang.Failureof Charisma:theCulturalRevolutionin","box":[[109,546],[797,547],[797,571],[109,570]]},{"text":"Wuhan.Oxford;NewYork:OxfordUniversityPress,1995","box":[[149,585],[664,585],[664,606],[149,606]]},{"text":"121.Wen,Chihua.TheRedMirror:ChildrenofChina'sCulturalRevolution","box":[[110,621],[793,623],[793,644],[110,642]]},{"text":"Boulder:WestviewPress,1995.","box":[[147,657],[425,658],[425,680],[147,678]]},{"text":"122.Wang,Norman.Cultural Revolution.NewYork:BallantineBooks,","box":[[109,694],[795,695],[795,718],[109,717]]},{"text":"Incorporated,1995.","box":[[148,733],[317,733],[317,754],[148,754]]},{"text":"123.Niu-Niu.No Tears for Mao: Growing up in the Cultural Revolution.","box":[[108,766],[795,767],[795,795],[108,794]]},{"text":"Chicago:Academy ChicagoPublishers,1995.","box":[[148,806],[547,806],[547,829],[148,829]]},{"text":"124.黄，《劉少奇的最後崴月：1966－1969》，中央文獻出版社’","box":[[109,841],[790,841],[790,865],[109,865]]},{"text":"1996年。","box":[[149,879],[230,879],[230,900],[149,900]]},{"text":"125.趙無眠，《文革大年表、渊源、革命、餘波》，明鏡出版社，1996年。","box":[[110,917],[783,917],[783,937],[110,937]]},{"text":"126.江渭清，《七十年征程》，江蘇人民出版社，1996年。","box":[[109,951],[666,953],[666,973],[109,972]]},{"text":"127.葉永烈，《張春橘傅》，作家出版社，1996年。","box":[[111,990],[601,990],[601,1010],[111,1010]]},{"text":"128.劉青峰，《文化大革命：史實舆研究》，香港中文大學出版社，","box":[[110,1027],[788,1027],[788,1048],[110,1048]]},{"text":"1996年。","box":[[149,1064],[230,1064],[230,1085],[149,1085]]},{"text":"129.李逊，《大崩：上海工人造反派興亡史》，時報文化出版企業有","box":[[111,1100],[795,1100],[795,1120],[111,1120]]},{"text":"限公司，1996年。","box":[[148,1138],[317,1138],[317,1159],[148,1159]]},{"text":"130.席宣、金春明，《「文化大革命」簡史》，中共中央出版社，1996年。","box":[[109,1173],[784,1174],[784,1195],[109,1194]]},{"text":"131.Schoenhals,Michael.China'sCulturalRevolution,1966-1969:Nota","box":[[110,1211],[797,1213],[797,1234],[110,1232]]}],"dimensions":{"height":1359,"width":945}}